CHANGES.rst
MANIFEST.in
README.rst
TODO.rst
setup.py
collective/__init__.py
collective.wfcomment.egg-info/PKG-INFO
collective.wfcomment.egg-info/SOURCES.txt
collective.wfcomment.egg-info/dependency_links.txt
collective.wfcomment.egg-info/entry_points.txt
collective.wfcomment.egg-info/namespace_packages.txt
collective.wfcomment.egg-info/not-zip-safe
collective.wfcomment.egg-info/requires.txt
collective.wfcomment.egg-info/top_level.txt
collective/wfcomment/__init__.py
collective/wfcomment/configure.zcml
collective/wfcomment/controlpanel.py
collective/wfcomment/interfaces.py
collective/wfcomment/testing.py
collective/wfcomment/upgrades.py
collective/wfcomment/wfcomment.py
collective/wfcomment/locales/collective.wfcomment.pot
collective/wfcomment/locales/update.sh
collective/wfcomment/locales/de/LC_MESSAGES/collective.wfcomment.po
collective/wfcomment/locales/fr/LC_MESSAGES/collective.wfcomment.po
collective/wfcomment/profiles/default/browserlayer.xml
collective/wfcomment/profiles/default/controlpanel.xml
collective/wfcomment/profiles/default/kssregistry.xml
collective/wfcomment/profiles/default/metadata.xml
collective/wfcomment/profiles/default/registry.xml
collective/wfcomment/tests/__init__.py
collective/wfcomment/tests/test_robot.py
collective/wfcomment/tests/robot/keywords.robot
collective/wfcomment/tests/robot/test_wfcomment.robot
docs/INSTALL.txt
docs/LICENSE.GPL
docs/LICENSE.txt
docs/screenshot-wfcomment.jpg