Metadata-Version: 1.1
Name: collective.wfcomment
Version: 2.1.5
Summary: Add a prompt on selected workflow transitions for the user to enter a comment
Home-page: http://pypi.python.org/pypi/collective.wfcomment
Author: Thomas Desvenain
Author-email: thomas.desvenain@gmail.com
License: GPL
Keywords: Plone workflow comment
Platform: UNKNOWN
Classifier: Framework :: Plone
Classifier: Programming Language :: Python
Classifier: Topic :: Software Development :: Libraries :: Python Modules
